banklist_ng/__init__.py
banklist_ng/banks data.json
banklist_ng/main.py
banklist_ng-0.0.1.dist-info/LICENSE
banklist_ng-0.0.1.dist-info/METADATA
banklist_ng-0.0.1.dist-info/WHEEL
banklist_ng-0.0.1.dist-info/top_level.txt
banklist_ng-0.0.1.dist-info/RECORD
