Metadata-Version: 2.1
Name: banklist_ng
Version: 0.0.1
Summary: Information about Nigerian banks including the bank's type, NIP code, name, slug, code, USSD, and logo.
Home-page: https://github.com/awesomegoodman/banklist-ng/tree/main/pypi
Author: Awesome Goodman
Author-email: goodman.awesome@gmail.com
Keywords: Nigerian Banks List,Nigerian Bank Codes,Nigerian Banks Logos,Banks in Nigeria
Classifier: Programming Language :: Python :: 3
Classifier: License :: OSI Approved :: MIT License
Classifier: Intended Audience :: Developers
Classifier: Operating System :: OS Independent
License-File: LICENSE
